{
  "ComponentIndexes": {},
  "ControlUniqueGuids": {},
  "ControlUniqueIds": {
    "addT": 18,
    "Adicionar": 32,
    "Adicionar_1": 45,
    "Adicionar_2": 58,
    "apagarEntrada1": 31,
    "apagarEntrada1_1": 44,
    "apagarEntrada1_2": 57,
    "App": 1,
    "bt2": 13,
    "bt3": 14,
    "bt4": 15,
    "calendario2": 28,
    "calendario2_1": 41,
    "calendario2_2": 54,
    "celndario": 27,
    "celndario_1": 40,
    "celndario_2": 53,
    "Checkbox2": 65,
    "Deletar": 33,
    "Deletar_1": 46,
    "Deletar_2": 59,
    "dellDown": 20,
    "dellUp": 19,
    "editar": 25,
    "editar_1": 38,
    "editar_2": 51,
    "entrada1": 30,
    "entrada1_1": 43,
    "entrada1_2": 56,
    "entrada2": 24,
    "entrada2_1": 37,
    "entrada2_2": 50,
    "entradaHora": 16,
    "entradaT": 17,
    "hora&data": 8,
    "Hora_Column1": 11,
    "horarios": 62,
    "Host": 3,
    "Icon12": 6,
    "menu": 7,
    "pendentes": 5,
    "recarregar": 9,
    "Saida1": 26,
    "Saida1_1": 39,
    "Saida1_2": 52,
    "seta1": 29,
    "seta1_1": 42,
    "seta1_2": 55,
    "Tabela1": 10,
    "Tarefa_Column1": 12,
    "tela1": 4,
    "tela2": 21,
    "tela2_1": 34,
    "tela2_2": 47,
    "titulo1": 22,
    "titulo1_1": 35,
    "titulo1_2": 48,
    "voltar": 23,
    "voltar_1": 36,
    "voltar_2": 49
  },
  "FunctionParamsInvariantScripts": {},
  "FunctionParamsInvariantScriptsOnInstances": {},
  "HeaderLastSavedDateTimeUTC": "07/25/2023 00:44:45",
  "IsLegacyComponentAllowGlobalScopeCase": false,
  "LocalConnectionIDReferences": {},
  "LocalDatabaseReferencesAsEmpty": false,
  "LocalResourceFileNames": {},
  "LocalResourceRootPaths": {},
  "OrderComponentMetadata": {},
  "OrderComponentTemplate": {},
  "OrderDataSource": {
    "ComboBoxSample": 1,
    "ListboxSample": 0,
    "tarefas": 2
  },
  "OrderGroupControls": {},
  "OrderPcfTemplate": {},
  "OrderTemplate": {},
  "OrderXMLTemplate": {
    "button": 2,
    "checkbox": 5,
    "combobox": 4,
    "datepicker": 6,
    "icon": 1,
    "label": 0,
    "text": 3
  },
  "OverridablePropertiesEntry": {
    "addT": {},
    "Adicionar": {},
    "Adicionar_1": {},
    "Adicionar_2": {},
    "apagarEntrada1": {},
    "apagarEntrada1_1": {},
    "apagarEntrada1_2": {},
    "App": {},
    "bt2": {},
    "bt3": {},
    "bt4": {},
    "calendario2": {},
    "calendario2_1": {},
    "calendario2_2": {},
    "celndario": {},
    "celndario_1": {},
    "celndario_2": {},
    "Checkbox2": {},
    "Deletar": {},
    "Deletar_1": {},
    "Deletar_2": {},
    "dellDown": {},
    "dellUp": {},
    "editar": {},
    "editar_1": {},
    "editar_2": {},
    "entrada1": {},
    "entrada1_1": {},
    "entrada1_2": {},
    "entrada2": {},
    "entrada2_1": {},
    "entrada2_2": {},
    "entradaHora": {},
    "entradaT": {},
    "hora&data": {},
    "Hora_Column1": {},
    "horarios": {},
    "Host": {},
    "Icon12": {},
    "menu": {},
    "pendentes": {},
    "recarregar": {},
    "Saida1": {},
    "Saida1_1": {},
    "Saida1_2": {},
    "seta1": {},
    "seta1_1": {},
    "seta1_2": {},
    "Tabela1": {},
    "Tarefa_Column1": {},
    "tela1": {},
    "tela2": {},
    "tela2_1": {},
    "tela2_2": {},
    "titulo1": {},
    "titulo1_1": {},
    "titulo1_2": {},
    "voltar": {},
    "voltar_1": {},
    "voltar_2": {}
  },
  "PCFDynamicSchemaForIRRetrievalEntry": {},
  "PCFTemplateEntry": {},
  "PublishOrderIndices": {
    "addT": 17,
    "Adicionar": 28,
    "Adicionar_1": 52,
    "Adicionar_2": 64,
    "apagarEntrada1": 27,
    "apagarEntrada1_1": 51,
    "apagarEntrada1_2": 63,
    "App": 0,
    "bt2": 7,
    "bt3": 8,
    "bt4": 9,
    "calendario2": 24,
    "calendario2_1": 48,
    "calendario2_2": 60,
    "celndario": 23,
    "celndario_1": 47,
    "celndario_2": 59,
    "Checkbox2": 13,
    "Deletar": 29,
    "Deletar_1": 53,
    "Deletar_2": 65,
    "dellDown": 15,
    "dellUp": 14,
    "editar": 21,
    "editar_1": 45,
    "editar_2": 57,
    "entrada1": 26,
    "entrada1_1": 50,
    "entrada1_2": 62,
    "entrada2": 20,
    "entrada2_1": 44,
    "entrada2_2": 56,
    "entradaHora": 10,
    "entradaT": 12,
    "hora&data": 2,
    "Hora_Column1": 5,
    "horarios": 11,
    "Host": 0,
    "Icon12": 16,
    "menu": 1,
    "pendentes": 0,
    "recarregar": 3,
    "Saida1": 22,
    "Saida1_1": 46,
    "Saida1_2": 58,
    "seta1": 25,
    "seta1_1": 49,
    "seta1_2": 61,
    "Tabela1": 4,
    "Tarefa_Column1": 6,
    "tela1": 0,
    "tela2": 0,
    "tela2_1": 0,
    "tela2_2": 0,
    "titulo1": 18,
    "titulo1_1": 42,
    "titulo1_2": 54,
    "voltar": 19,
    "voltar_1": 43,
    "voltar_2": 55
  },
  "ResourcesJsonIndices": {},
  "RuleScreenIdWithoutScreen": {},
  "TemplateVersions": {},
  "VolatileProperties": {
    "AnalysisLoadTime": 0.3410036,
    "ControlCount": {
      "button": 20,
      "dataTable": 1,
      "dataTableColumn": 2,
      "datepicker": 8,
      "icon": 45,
      "label": 10,
      "screen": 9,
      "text": 26
    },
    "DeserializationLoadTime": 0.8171537
  },
  "WasLocalDatabaseReferencesEmpty": true
}